ajal_todo_cli/__init__.py
ajal_todo_cli/__main__.py
ajal_todo_cli/app.py
ajal_todo_cli-0.1.2.dist-info/METADATA
ajal_todo_cli-0.1.2.dist-info/WHEEL
ajal_todo_cli-0.1.2.dist-info/entry_points.txt
ajal_todo_cli-0.1.2.dist-info/top_level.txt
ajal_todo_cli-0.1.2.dist-info/RECORD
