Metadata-Version: 2.1
Name: ajal-todo-cli
Version: 0.1.2
Summary: Add your description here
Classifier: Development Status :: 3 - Alpha
Classifier: Environment :: Console
Classifier: Topic :: Education
Requires-Python: >=3.12
Requires-Dist: typer >=0.13.0
